textvision/detectors.py
textvision-0.3.0.dist-info/entry_points.txt
textvision-0.3.0.dist-info/WHEEL
textvision-0.3.0.dist-info/METADATA
textvision-0.3.0.dist-info/RECORD
