Metadata-Version: 2.1
Name: textvision
Version: 0.3.0
Summary: textvision uses the Google Vision API to perform OCR and return text.
License: MIT
Author: Sean Davis
Author-email: seandavi@gmail.com
Requires-Python: >=3.8,<4.0
Classifier: License :: OSI Approved :: MIT License
Classifier: Programming Language :: Python :: 3
Classifier: Programming Language :: Python :: 3.8
Classifier: Programming Language :: Python :: 3.9
Requires-Dist: click (>=7.1.2,<8.0.0)
Requires-Dist: google-cloud-vision (>=2.3.0,<3.0.0)
